MANIFEST.in
PyCrypterFUD.py
setup.py
ceshigogogo/__init__.py
ceshigogogo.egg-info/PKG-INFO
ceshigogogo.egg-info/SOURCES.txt
ceshigogogo.egg-info/dependency_links.txt
ceshigogogo.egg-info/requires.txt
ceshigogogo.egg-info/top_level.txt