Metadata-Version: 2.2
Name: ceshigogogo
Version: 0.1
Requires-Dist: requests>=2.25.1
Dynamic: requires-dist
